soft_computing/__init__.py
soft_computing-0.0.0.dist-info/METADATA
soft_computing-0.0.0.dist-info/WHEEL
soft_computing-0.0.0.dist-info/RECORD
